dops/__init__.py
dops/__main__.py
dops/config.py
dops/version.py
dops/core/__init__.py
dops/core/logger.py
dops/core/install/__init__.py
dops/core/install/base.py
dops/core/install/instance/__init__.py
dops/core/install/instance/general.py
dops/core/install/network/__init__.py
dops/plugins/__init__.py
dops/plugins/node.py
dops/plugins/utils/__init__.py
dops/subcmd/__init__.py
dops/subcmd/get.py
dops/subcmd/install.py
dops/subcmd/version.py
dops-0.0.1.36.data/data/share/doc/dops/README.rst
dops-0.0.1.36.dist-info/DESCRIPTION.rst
dops-0.0.1.36.dist-info/METADATA
dops-0.0.1.36.dist-info/RECORD
dops-0.0.1.36.dist-info/WHEEL
dops-0.0.1.36.dist-info/entry_points.txt
dops-0.0.1.36.dist-info/metadata.json
dops-0.0.1.36.dist-info/top_level.txt
